head_direction/__init__.py
head_direction/head.py
head_direction/tools.py
head_direction-0.1.0.dist-info/LICENSE
head_direction-0.1.0.dist-info/METADATA
head_direction-0.1.0.dist-info/WHEEL
head_direction-0.1.0.dist-info/top_level.txt
head_direction-0.1.0.dist-info/RECORD
