Metadata-Version: 2.1
Name: head_direction
Version: 0.1.0
Summary: Analysis of head direction cells.
Author-email: Mikkel Lepperod <mikkel@simula.no>, Alessio Buccino <alessiop.buccino@gmail.com>
Project-URL: homepage, https://github.com/CINPLA/head-directopm
Project-URL: repository, https://github.com/CINPLA/head-direction
Classifier: Programming Language :: Python :: 3
Classifier: License :: OSI Approved :: MIT License
Classifier: Operating System :: OS Independent
Requires-Python: >=3.10
License-File: LICENSE
Requires-Dist: numpy<2
Requires-Dist: scipy
Requires-Dist: astropy
Requires-Dist: pycircstat
Requires-Dist: pandas
Requires-Dist: elephant
Requires-Dist: matplotlib
Requires-Dist: nose
Provides-Extra: dev
Requires-Dist: pre-commit; extra == "dev"
Requires-Dist: black[jupyter]; extra == "dev"
Requires-Dist: isort; extra == "dev"
Requires-Dist: ruff; extra == "dev"
Provides-Extra: test
Requires-Dist: pytest; extra == "test"
Requires-Dist: pytest-cov; extra == "test"
Requires-Dist: pytest-dependency; extra == "test"
Requires-Dist: mountainsort5; extra == "test"
Provides-Extra: docs
Requires-Dist: sphinx-gallery; extra == "docs"
Requires-Dist: sphinx_rtd_theme; extra == "docs"
Provides-Extra: full
Requires-Dist: head_direction[dev]; extra == "full"
Requires-Dist: head_direction[test]; extra == "full"
Requires-Dist: head_direction[docs]; extra == "full"
